j3/api.py
j3/command.py
j3/config.py
j3/event.py
j3/logging.py
j3/orm.py
j3/py.typed
j3/redis.py
j3/reloader.py
j3/repo.py
j3/schema.py
j3/uow.py
j3/utils.py
j3/core/__init__.py
j3/core/_errors.py
j3/core/_logging.py
j3/core/_models.py
j3/core/_uow.py
j3/core/py.typed
j3/templates/app/.gitignore
j3/templates/app/README.md.j2
j3/templates/app/requirements.txt
j3/templates/app/setup.cfg.j2
j3/templates/app/.vscode/settings.json
j3/templates/app/app/__init__.py
j3/templates/app/app/__main__.py
j3/templates/app/app/config.py.j2
j3/templates/app/app/adapters/__init__.py
j3/templates/app/app/adapters/orm/__init__.py
j3/templates/app/app/adapters/orm/default.py.j2
j3/templates/app/app/domain/__init__.py
j3/templates/app/app/domain/aggregates.py
j3/templates/app/app/domain/events.py
j3/templates/app/app/domain/models.py
j3/templates/app/app/handlers/__init__.py
j3/templates/app/app/handlers/sample.py
j3/templates/app/app/routes/__init__.py
j3/templates/app/app/routes/sample.py
j3/templates/app/app/schema/__init__.py
j3/templates/app/app/schema/sample.py
j3/templates/app/app/services/__init__.py
j3/templates/app/app/services/sample.py
j3/templates/app/tests/__init__.py
j3/templates/app/tests/conftest.py
j3/templates/app/tests/e2e/__init__.py
j3/templates/app/tests/e2e/test_api.py
j3/templates/app/tests/integration/__init__.py
j3/templates/app/tests/integration/test_orm.py
j3/templates/app/tests/integration/test_repository.py
j3/templates/app/tests/integration/test_uow.py
j3/templates/app/tests/unit/__init__.py
j3/templates/app/tests/unit/test_domain.py.j2
j3/templates/app/tests/unit/test_services.py.j2
j3/test/__init__.py
j3/test/api.py
j3/test/e2e.py
j3/test/py.typed
j3/test/unit.py
j3/test/utils.py
j3_framework-0.5.1.dist-info/METADATA
j3_framework-0.5.1.dist-info/WHEEL
j3_framework-0.5.1.dist-info/entry_points.txt
j3_framework-0.5.1.dist-info/top_level.txt
j3_framework-0.5.1.dist-info/RECORD
