Metadata-Version: 2.1
Name: j3-framework
Version: 0.5.1
Summary: J3 Framework - full-stack framework for microservice architecture applications
Home-page: https://dev.azure.com/j3-project/smartstock/_git/j3
Author: Joseph Kim
Author-email: cloudeyes@gmail.com
License: MIT
Download-URL: https://github.com/j3-project/j3/archive/v0.5.1.tar.gz
Keywords: j3,microserviceframework,sqlalchemy,fastapi
Platform: UNKNOWN
Classifier: Development Status :: 3 - Alpha
Classifier: Intended Audience :: Developers
Classifier: Topic :: Software Development :: Build Tools
Classifier: License :: OSI Approved :: MIT License
Classifier: Programming Language :: Python :: 3.9
Requires-Dist: fastapi
Requires-Dist: uvicorn
Requires-Dist: sqlalchemy
Requires-Dist: jinja2
Requires-Dist: colorama
Requires-Dist: tenacity
Requires-Dist: aioredis
Requires-Dist: httpx
Requires-Dist: requests
